{
  "format-version" : 2,
  "table-uuid" : "9e578988-dd66-411d-8410-8d0444ad8ec9",
  "location" : "warehouse/bronze/fact_lead_events",
  "last-sequence-number" : 6,
  "last-updated-ms" : 1783308936222,
  "last-column-id" : 8,
  "current-schema-id" : 0,
  "schemas" : [ {
    "type" : "struct",
    "schema-id" : 0,
    "fields" : [ {
      "id" : 1,
      "name" : "lead_event_key",
      "required" : false,
      "type" : "long"
    }, {
      "id" : 2,
      "name" : "lead_id",
      "required" : false,
      "type" : "string"
    }, {
      "id" : 3,
      "name" : "date_key",
      "required" : false,
      "type" : "int"
    }, {
      "id" : 4,
      "name" : "customer_key",
      "required" : false,
      "type" : "int"
    }, {
      "id" : 5,
      "name" : "channel_key",
      "required" : false,
      "type" : "int"
    }, {
      "id" : 6,
      "name" : "event_timestamp",
      "required" : false,
      "type" : "timestamptz"
    }, {
      "id" : 7,
      "name" : "lead_status",
      "required" : false,
      "type" : "string"
    }, {
      "id" : 8,
      "name" : "event_date",
      "required" : false,
      "type" : "date"
    } ]
  } ],
  "default-spec-id" : 0,
  "partition-specs" : [ {
    "spec-id" : 0,
    "fields" : [ {
      "name" : "event_date_day",
      "transform" : "day",
      "source-id" : 8,
      "field-id" : 1000
    } ]
  } ],
  "last-partition-id" : 1000,
  "default-sort-order-id" : 0,
  "sort-orders" : [ {
    "order-id" : 0,
    "fields" : [ ]
  } ],
  "properties" : {
    "owner" : "nishan.duwal",
    "write.parquet.compression-codec" : "zstd"
  },
  "current-snapshot-id" : 5719792728007775708,
  "refs" : {
    "main" : {
      "snapshot-id" : 5719792728007775708,
      "type" : "branch"
    }
  },
  "snapshots" : [ {
    "sequence-number" : 1,
    "snapshot-id" : 2516478274825184324,
    "timestamp-ms" : 1783308919506,
    "summary" : {
      "operation" : "append",
      "spark.app.id" : "local-1783308870963",
      "added-data-files" : "162",
      "added-records" : "312",
      "added-files-size" : "387256",
      "changed-partition-count" : "162",
      "total-records" : "312",
      "total-files-size" : "387256",
      "total-data-files" : "162",
      "total-delete-files" : "0",
      "total-position-deletes" : "0",
      "total-equality-deletes" : "0"
    },
    "manifest-list" : "warehouse/bronze/fact_lead_events/metadata/snap-2516478274825184324-1-1805dc66-e1f0-4555-864d-485f2b1db35d.avro",
    "schema-id" : 0
  }, {
    "sequence-number" : 2,
    "snapshot-id" : 7438936634202768282,
    "parent-snapshot-id" : 2516478274825184324,
    "timestamp-ms" : 1783308922862,
    "summary" : {
      "operation" : "append",
      "spark.app.id" : "local-1783308870963",
      "added-data-files" : "346",
      "added-records" : "1390",
      "added-files-size" : "869228",
      "changed-partition-count" : "346",
      "total-records" : "1702",
      "total-files-size" : "1256484",
      "total-data-files" : "508",
      "total-delete-files" : "0",
      "total-position-deletes" : "0",
      "total-equality-deletes" : "0"
    },
    "manifest-list" : "warehouse/bronze/fact_lead_events/metadata/snap-7438936634202768282-1-e7bd9c41-ec23-4ee5-a2d1-f4604507d83b.avro",
    "schema-id" : 0
  }, {
    "sequence-number" : 3,
    "snapshot-id" : 8638284908141812202,
    "parent-snapshot-id" : 7438936634202768282,
    "timestamp-ms" : 1783308926164,
    "summary" : {
      "operation" : "append",
      "spark.app.id" : "local-1783308870963",
      "added-data-files" : "364",
      "added-records" : "2591",
      "added-files-size" : "954700",
      "changed-partition-count" : "364",
      "total-records" : "4293",
      "total-files-size" : "2211184",
      "total-data-files" : "872",
      "total-delete-files" : "0",
      "total-position-deletes" : "0",
      "total-equality-deletes" : "0"
    },
    "manifest-list" : "warehouse/bronze/fact_lead_events/metadata/snap-8638284908141812202-1-8fe80336-ebe0-47d6-9477-1e81175a6f1d.avro",
    "schema-id" : 0
  }, {
    "sequence-number" : 4,
    "snapshot-id" : 2941758356095157544,
    "parent-snapshot-id" : 8638284908141812202,
    "timestamp-ms" : 1783308929490,
    "summary" : {
      "operation" : "append",
      "spark.app.id" : "local-1783308870963",
      "added-data-files" : "365",
      "added-records" : "3484",
      "added-files-size" : "980809",
      "changed-partition-count" : "365",
      "total-records" : "7777",
      "total-files-size" : "3191993",
      "total-data-files" : "1237",
      "total-delete-files" : "0",
      "total-position-deletes" : "0",
      "total-equality-deletes" : "0"
    },
    "manifest-list" : "warehouse/bronze/fact_lead_events/metadata/snap-2941758356095157544-1-08fa8c83-c2ef-4d48-aacd-055b19a450a9.avro",
    "schema-id" : 0
  }, {
    "sequence-number" : 5,
    "snapshot-id" : 6792272990231710230,
    "parent-snapshot-id" : 2941758356095157544,
    "timestamp-ms" : 1783308932903,
    "summary" : {
      "operation" : "append",
      "spark.app.id" : "local-1783308870963",
      "added-data-files" : "365",
      "added-records" : "5096",
      "added-files-size" : "1017637",
      "changed-partition-count" : "365",
      "total-records" : "12873",
      "total-files-size" : "4209630",
      "total-data-files" : "1602",
      "total-delete-files" : "0",
      "total-position-deletes" : "0",
      "total-equality-deletes" : "0"
    },
    "manifest-list" : "warehouse/bronze/fact_lead_events/metadata/snap-6792272990231710230-1-cc41b014-a978-4775-9baa-fecc81ee09f0.avro",
    "schema-id" : 0
  }, {
    "sequence-number" : 6,
    "snapshot-id" : 5719792728007775708,
    "parent-snapshot-id" : 6792272990231710230,
    "timestamp-ms" : 1783308936222,
    "summary" : {
      "operation" : "append",
      "spark.app.id" : "local-1783308870963",
      "added-data-files" : "365",
      "added-records" : "6615",
      "added-files-size" : "1041634",
      "changed-partition-count" : "365",
      "total-records" : "19488",
      "total-files-size" : "5251264",
      "total-data-files" : "1967",
      "total-delete-files" : "0",
      "total-position-deletes" : "0",
      "total-equality-deletes" : "0"
    },
    "manifest-list" : "warehouse/bronze/fact_lead_events/metadata/snap-5719792728007775708-1-69f00cf7-bf5e-455f-b67c-8341a75e8dd0.avro",
    "schema-id" : 0
  } ],
  "statistics" : [ ],
  "partition-statistics" : [ ],
  "snapshot-log" : [ {
    "timestamp-ms" : 1783308919506,
    "snapshot-id" : 2516478274825184324
  }, {
    "timestamp-ms" : 1783308922862,
    "snapshot-id" : 7438936634202768282
  }, {
    "timestamp-ms" : 1783308926164,
    "snapshot-id" : 8638284908141812202
  }, {
    "timestamp-ms" : 1783308929490,
    "snapshot-id" : 2941758356095157544
  }, {
    "timestamp-ms" : 1783308932903,
    "snapshot-id" : 6792272990231710230
  }, {
    "timestamp-ms" : 1783308936222,
    "snapshot-id" : 5719792728007775708
  } ],
  "metadata-log" : [ {
    "timestamp-ms" : 1783308919506,
    "metadata-file" : "warehouse/bronze/fact_lead_events/metadata/v1.metadata.json"
  }, {
    "timestamp-ms" : 1783308922862,
    "metadata-file" : "warehouse/bronze/fact_lead_events/metadata/v2.metadata.json"
  }, {
    "timestamp-ms" : 1783308926164,
    "metadata-file" : "warehouse/bronze/fact_lead_events/metadata/v3.metadata.json"
  }, {
    "timestamp-ms" : 1783308929490,
    "metadata-file" : "warehouse/bronze/fact_lead_events/metadata/v4.metadata.json"
  }, {
    "timestamp-ms" : 1783308932903,
    "metadata-file" : "warehouse/bronze/fact_lead_events/metadata/v5.metadata.json"
  } ]
}